fyers_api_builder/__init__.py
fyers_api_builder/main.py
fyers_api_builder/libs/__init__.py
fyers_api_builder/libs/generate_payload.py
fyers_api_builder/libs/generate_tasks.py
fyers_api_builder/libs/get_history_data.py
fyers_api_builder-0.3.8.dist-info/LICENSE
fyers_api_builder-0.3.8.dist-info/METADATA
fyers_api_builder-0.3.8.dist-info/WHEEL
fyers_api_builder-0.3.8.dist-info/top_level.txt
fyers_api_builder-0.3.8.dist-info/RECORD
