Metadata-Version: 2.1
Name: fyers-api-builder
Version: 0.3.8
Summary: Fyers Api Builder
Home-page: https://github.com/krunaldodiya/fyers-api-builder
Author: Krunal Dodiya
Author-email: kunal.dodiya1@gmail.com
License: UNKNOWN
Platform: UNKNOWN
Classifier: Programming Language :: Python :: 3
Classifier: Operating System :: OS Independent
License-File: LICENSE
Requires-Dist: requests
